ram_dp_async.v
module ram_dp_async
        #(parameter DEPTH = 16,
          parameter WIDTH = 8,
          parameter DEPTH_LOG = $clog2(DEPTH))
          (
            input clk,
            input wr_en,
            input [DEPTH_LOG-1:0] addr_wr,
            input [DEPTH_LOG-1:0] addr_rd,
            input [WIDTH-1:0] data_wr,
            output [WIDTH-1:0] data_rd
          );

          reg [WIDTH-1:0] ram [0:DEPTH-1];

          always @(posedge clk ) begin

            if(wr_en) begin
                ram[addr_wr] <= data_wr;
            end

          end

          assign data_rd = ram[addr_rd];

endmodule

data_transfer_fsm.v
`include "ram_dp_async.v"

module data_transfer_fsm(
    input clk,
    input rset,
    //signal for input sram
    input ram_in_we,
    input [4:0] ram_in_addr_wr,
    input [7:0] ram_in_data_wr,
    //signal for output sram
    input [3:0] ram_out_addr_rd,
    output [15:0] ram_out_data_rd,
    //fsm control signals
    input opmode_in,
    output reg done_out
);

    parameter [3:0] IDLE = 4'b0001,
                    READ_BY0 = 4'b0010,
                    READ_BY1 = 4'b0100,
                    WRITE_BY12 = 4'b1000;

    //fsm state logic
    reg [3:0] state,next_state;

    //used to read from ram_in and write in ram_out
    reg [4:0] ram_pointer;

    reg [4:0] fsm_mem_in_addr_rd;
    wire [7:0] fsm_mem_in_data_rd;
    reg [7:0] read_byte0_buffer,read_byte1_buffer;

    reg [3:0] fsm_mem_out_addr_wr;
    reg ram_out_we;

    //instantiate the RAM modules
    ram_dp_async #(.WIDTH(8),.DEPTH(32))
            RAM_IN(
                .clk(clk),
                .wr_en(ram_in_we),
                .addr_wr(ram_in_addr_wr),
                .data_wr(ram_in_data_wr),
                .addr_rd(fsm_mem_in_addr_rd),
                .data_rd(fsm_mem_in_data_rd)
            );

    ram_dp_async #(.WIDTH(16),.DEPTH(16))
            RAM_OUT(
                .clk(clk),
                .wr_en(ram_out_we),
                .addr_wr(fsm_mem_out_addr_wr),
                .data_wr({read_byte0_buffer,read_byte1_buffer}),
                .addr_rd(ram_out_addr_rd),
                .data_rd(ram_out_data_rd)
            );

    always @(*) begin
    next_state = IDLE;
    fsm_mem_in_addr_rd = 0;
    ram_out_we = 0;
    case(state)
        IDLE:
            if (opmode_in) next_state = READ_BY0;
        READ_BY0: begin
            fsm_mem_in_addr_rd = ram_pointer;
            next_state = READ_BY1;
        end
        READ_BY1: begin
            fsm_mem_in_addr_rd = ram_pointer;
            next_state = WRITE_BY12;
        end
        WRITE_BY12: begin
            ram_out_we = 1;
            next_state = (done_out ? IDLE : READ_BY0);
        end
        default: next_state = IDLE;
    endcase
end

    always @(posedge clk or negedge rset) begin
        if(!rset)
            state <= IDLE;
        else
            state <= next_state;
    end

    always @(posedge clk or negedge rset) begin
        if(!rset)
            ram_pointer <= 0;
        else if((state == READ_BY0) || (state == READ_BY1))
            ram_pointer <= ram_pointer + 1'b1;
    end

    always @(posedge clk or negedge rset) begin
        if(!rset)
            fsm_mem_out_addr_wr <= 0;
        else if (state == READ_BY0)
            fsm_mem_out_addr_wr <= (ram_pointer >> 1);
    end

    always @(posedge clk or negedge rset) begin
        if(!rset)
            done_out <= 0;
        else if (opmode_in ==  1)
            done_out <= 0;
        else if (ram_pointer == 5'd31)
            done_out <= 1;
    end

    always @(posedge clk or negedge rset) begin
        if(!rset) begin
            read_byte0_buffer <= 0;
            read_byte1_buffer <= 0;
        end else begin
            read_byte0_buffer <= fsm_mem_in_data_rd;
            read_byte1_buffer <= read_byte0_buffer;
        end
    end

endmodule

tb_data_transfer_fsm.v
`include "data_transfer_fsm.v"
module tb_data_transfer_fsm();
     
     localparam DEPTH = 4;
     localparam WIDTH_WR = 8;

     reg clk = 0;
     reg rset;
     reg we;
     reg [4:0] addr_wr;
     reg [3:0] addr_rd;
     reg [WIDTH_WR-1:0] data_wr;
     wire [2*WIDTH_WR-1:0] data_rd;
     reg [2*WIDTH_WR-1:0] data_rd_buff;
     wire done;
     reg opmode;
     reg [2*WIDTH_WR-1:0] data_exp;

     integer i,loop_no;

     integer test_count = 0,success_count = 0,error_count = 0;

     data_transfer_fsm DTF(
        .clk(clk),
        .rset(rset),
        .ram_in_we(we),
        .ram_in_addr_wr(addr_wr),
        .ram_in_data_wr(data_wr),
        .ram_out_addr_rd(addr_rd),
        .ram_out_data_rd(data_rd),
        .opmode_in(opmode),
        .done_out(done)
     );

     always #0.5 clk = ~ clk;

     task write_data (input [4:0]addr_in,input [WIDTH_WR-1:0]data_in);
        begin
            @(posedge clk);
            we = 1;
            data_wr = data_in;
            addr_wr = addr_in;
            $display($time," write_address = %d data_wr = 0x%h",addr_wr,data_wr);
            @(posedge clk);
            we = 0;
        end
     endtask

     task read_data (input [3:0]addr_in);
        begin
            @(posedge clk);
            addr_rd = addr_in;
            @(negedge clk);
            $display($time," read_address = %d data_rd = 0x%h",addr_rd,data_rd);
            data_rd_buff = data_rd;
        end
     endtask

     task compare_data(input [2*WIDTH_WR-1:0] expected , input [2*WIDTH_WR-1:0]observed);
        begin
            test_count = test_count + 1;
            if(observed === expected) begin
                success_count = success_count + 1;
            end else begin
                error_count = error_count + 1;
            end
        end
     endtask

     initial begin
        we = 0;
        addr_wr = 0;
        opmode = 0;
        rset = 0;
        #10;
        rset = 1;

        for(loop_no=0;loop_no<2;loop_no=loop_no+1) begin
            //fills the ram with certain pattern
            for(i=0;i<32;i=i+1) begin
                write_data(i,((i%2)<<7) + i + loop_no);
            end
        

            @(posedge clk);opmode = 1;
             @(posedge clk);opmode = 0;

             @(posedge clk);wait(done === 1);
            for(i = 0;i<32;i=i+2)begin
                read_data(i>>1);
                data_exp = ((((i%2)<<7)+i+loop_no)<<8) | ((((i+1)%2)<<7)+(i+loop_no+1));
                compare_data(data_exp,data_rd_buff);
            end
        end

        #40;
        $display($time,"test_count = %d | success_count = %d | error_count = %d",test_count,success_count,error_count);
        $finish;

     end

     initial begin
        $dumpfile("data_transfer_fsm.vcd");
        $dumpvars(0,tb_data_transfer_fsm);
     end

endmodule

data_transfer_fsm.vcd
$date
	Thu Oct 23 00:53:15 2025
$end
$version
	Icarus Verilog
$end
$timescale
	1s
$end
$scope module tb_data_transfer_fsm $end
$var wire 1 ! done $end
$var wire 16 " data_rd [15:0] $end
$var parameter 32 # DEPTH $end
$var parameter 32 $ WIDTH_WR $end
$var reg 4 % addr_rd [3:0] $end
$var reg 5 & addr_wr [4:0] $end
$var reg 1 ' clk $end
$var reg 16 ( data_exp [15:0] $end
$var reg 16 ) data_rd_buff [15:0] $end
$var reg 8 * data_wr [7:0] $end
$var reg 1 + opmode $end
$var reg 1 , rset $end
$var reg 1 - we $end
$var integer 32 . error_count [31:0] $end
$var integer 32 / i [31:0] $end
$var integer 32 0 loop_no [31:0] $end
$var integer 32 1 success_count [31:0] $end
$var integer 32 2 test_count [31:0] $end
$scope module DTF $end
$var wire 1 ' clk $end
$var wire 1 + opmode_in $end
$var wire 5 3 ram_in_addr_wr [4:0] $end
$var wire 8 4 ram_in_data_wr [7:0] $end
$var wire 1 - ram_in_we $end
$var wire 4 5 ram_out_addr_rd [3:0] $end
$var wire 1 , rset $end
$var wire 16 6 ram_out_data_rd [15:0] $end
$var wire 8 7 fsm_mem_in_data_rd [7:0] $end
$var parameter 4 8 IDLE $end
$var parameter 4 9 READ_BY0 $end
$var parameter 4 : READ_BY1 $end
$var parameter 4 ; WRITE_BY12 $end
$var reg 1 ! done_out $end
$var reg 5 < fsm_mem_in_addr_rd [4:0] $end
$var reg 4 = fsm_mem_out_addr_wr [3:0] $end
$var reg 4 > next_state [3:0] $end
$var reg 1 ? ram_out_we $end
$var reg 5 @ ram_pointer [4:0] $end
$var reg 8 A read_byte0_buffer [7:0] $end
$var reg 8 B read_byte1_buffer [7:0] $end
$var reg 4 C state [3:0] $end
$scope module RAM_IN $end
$var wire 5 D addr_rd [4:0] $end
$var wire 5 E addr_wr [4:0] $end
$var wire 1 ' clk $end
$var wire 8 F data_rd [7:0] $end
$var wire 8 G data_wr [7:0] $end
$var wire 1 - wr_en $end
$var parameter 32 H DEPTH $end
$var parameter 32 I DEPTH_LOG $end
$var parameter 32 J WIDTH $end
$upscope $end
$scope module RAM_OUT $end
$var wire 4 K addr_rd [3:0] $end
$var wire 4 L addr_wr [3:0] $end
$var wire 1 ' clk $end
$var wire 16 M data_rd [15:0] $end
$var wire 16 N data_wr [15:0] $end
$var wire 1 ? wr_en $end
$var parameter 32 O DEPTH $end
$var parameter 32 P DEPTH_LOG $end
$var parameter 32 Q WIDTH $end
$upscope $end
$upscope $end
$scope task compare_data $end
$var reg 16 R expected [15:0] $end
$var reg 16 S observed [15:0] $end
$upscope $end
$scope task read_data $end
$var reg 4 T addr_in [3:0] $end
$upscope $end
$scope task write_data $end
$var reg 5 U addr_in [4:0] $end
$var reg 8 V data_in [7:0] $end
$upscope $end
$upscope $end
$enddefinitions $end
$comment Show the parameter values. $end
$dumpall
b10000 Q
b100 P
b10000 O
b1000 J
b101 I
b100000 H
b1000 ;
b100 :
b10 9
b1 8
b1000 $
b100 #
$end
#0
$dumpvars
bx V
bx U
bx T
bx S
bx R
b0 N
bx M
b0 L
bx K
bx G
bx F
b0 E
b0 D
b1 C
b0 B
b0 A
b0 @
0?
b1 >
b0 =
b0 <
bx 7
bx 6
bx 5
bx 4
b0 3
b0 2
b0 1
bx 0
bx /
b0 .
0-
0,
0+
bx *
bx )
bx (
0'
b0 &
bx %
bx "
0!
$end
#1
1'
#2
0'
#3
1'
#4
0'
#5
1'
#6
0'
#7
1'
#8
0'
#9
1'
#10
0'
b0 V
b0 U
b0 /
b0 0
1,
#11
b0 7
b0 F
bx00000000 N
bx A
b0 *
b0 4
b0 G
1-
1'
#12
0'
#13
bx B
b0xxxxxxxx N
b0 A
b10000001 V
b1 U
b1 /
0-
1'
#14
0'
#15
b0 N
b0 B
b1 &
b1 3
b1 E
b10000001 *
b10000001 4
b10000001 G
1-
1'
#16
0'
#17
b10 V
b10 U
b10 /
0-
1'
#18
0'
#19
b10 &
b10 3
b10 E
b10 *
b10 4
b10 G
1-
1'
#20
0'
#21
b10000011 V
b11 U
b11 /
0-
1'
#22
0'
#23
b11 &
b11 3
b11 E
b10000011 *
b10000011 4
b10000011 G
1-
1'
#24
0'
#25
b100 V
b100 U
b100 /
0-
1'
#26
0'
#27
b100 &
b100 3
b100 E
b100 *
b100 4
b100 G
1-
1'
#28
0'
#29
b10000101 V
b101 U
b101 /
0-
1'
#30
0'
#31
b101 &
b101 3
b101 E
b10000101 *
b10000101 4
b10000101 G
1-
1'
#32
0'
#33
b110 V
b110 U
b110 /
0-
1'
#34
0'
#35
b110 &
b110 3
b110 E
b110 *
b110 4
b110 G
1-
1'
#36
0'
#37
b10000111 V
b111 U
b111 /
0-
1'
#38
0'
#39
b111 &
b111 3
b111 E
b10000111 *
b10000111 4
b10000111 G
1-
1'
#40
0'
#41
b1000 V
b1000 U
b1000 /
0-
1'
#42
0'
#43
b1000 &
b1000 3
b1000 E
b1000 *
b1000 4
b1000 G
1-
1'
#44
0'
#45
b10001001 V
b1001 U
b1001 /
0-
1'
#46
0'
#47
b1001 &
b1001 3
b1001 E
b10001001 *
b10001001 4
b10001001 G
1-
1'
#48
0'
#49
b1010 V
b1010 U
b1010 /
0-
1'
#50
0'
#51
b1010 &
b1010 3
b1010 E
b1010 *
b1010 4
b1010 G
1-
1'
#52
0'
#53
b10001011 V
b1011 U
b1011 /
0-
1'
#54
0'
#55
b1011 &
b1011 3
b1011 E
b10001011 *
b10001011 4
b10001011 G
1-
1'
#56
0'
#57
b1100 V
b1100 U
b1100 /
0-
1'
#58
0'
#59
b1100 &
b1100 3
b1100 E
b1100 *
b1100 4
b1100 G
1-
1'
#60
0'
#61
b10001101 V
b1101 U
b1101 /
0-
1'
#62
0'
#63
b1101 &
b1101 3
b1101 E
b10001101 *
b10001101 4
b10001101 G
1-
1'
#64
0'
#65
b1110 V
b1110 U
b1110 /
0-
1'
#66
0'
#67
b1110 &
b1110 3
b1110 E
b1110 *
b1110 4
b1110 G
1-
1'
#68
0'
#69
b10001111 V
b1111 U
b1111 /
0-
1'
#70
0'
#71
b1111 &
b1111 3
b1111 E
b10001111 *
b10001111 4
b10001111 G
1-
1'
#72
0'
#73
b10000 V
b10000 U
b10000 /
0-
1'
#74
0'
#75
b10000 &
b10000 3
b10000 E
b10000 *
b10000 4
b10000 G
1-
1'
#76
0'
#77
b10010001 V
b10001 U
b10001 /
0-
1'
#78
0'
#79
b10001 &
b10001 3
b10001 E
b10010001 *
b10010001 4
b10010001 G
1-
1'
#80
0'
#81
b10010 V
b10010 U
b10010 /
0-
1'
#82
0'
#83
b10010 &
b10010 3
b10010 E
b10010 *
b10010 4
b10010 G
1-
1'
#84
0'
#85
b10010011 V
b10011 U
b10011 /
0-
1'
#86
0'
#87
b10011 &
b10011 3
b10011 E
b10010011 *
b10010011 4
b10010011 G
1-
1'
#88
0'
#89
b10100 V
b10100 U
b10100 /
0-
1'
#90
0'
#91
b10100 &
b10100 3
b10100 E
b10100 *
b10100 4
b10100 G
1-
1'
#92
0'
#93
b10010101 V
b10101 U
b10101 /
0-
1'
#94
0'
#95
b10101 &
b10101 3
b10101 E
b10010101 *
b10010101 4
b10010101 G
1-
1'
#96
0'
#97
b10110 V
b10110 U
b10110 /
0-
1'
#98
0'
#99
b10110 &
b10110 3
b10110 E
b10110 *
b10110 4
b10110 G
1-
1'
#100
0'
#101
b10010111 V
b10111 U
b10111 /
0-
1'
#102
0'
#103
b10111 &
b10111 3
b10111 E
b10010111 *
b10010111 4
b10010111 G
1-
1'
#104
0'
#105
b11000 V
b11000 U
b11000 /
0-
1'
#106
0'
#107
b11000 &
b11000 3
b11000 E
b11000 *
b11000 4
b11000 G
1-
1'
#108
0'
#109
b10011001 V
b11001 U
b11001 /
0-
1'
#110
0'
#111
b11001 &
b11001 3
b11001 E
b10011001 *
b10011001 4
b10011001 G
1-
1'
#112
0'
#113
b11010 V
b11010 U
b11010 /
0-
1'
#114
0'
#115
b11010 &
b11010 3
b11010 E
b11010 *
b11010 4
b11010 G
1-
1'
#116
0'
#117
b10011011 V
b11011 U
b11011 /
0-
1'
#118
0'
#119
b11011 &
b11011 3
b11011 E
b10011011 *
b10011011 4
b10011011 G
1-
1'
#120
0'
#121
b11100 V
b11100 U
b11100 /
0-
1'
#122
0'
#123
b11100 &
b11100 3
b11100 E
b11100 *
b11100 4
b11100 G
1-
1'
#124
0'
#125
b10011101 V
b11101 U
b11101 /
0-
1'
#126
0'
#127
b11101 &
b11101 3
b11101 E
b10011101 *
b10011101 4
b10011101 G
1-
1'
#128
0'
#129
b11110 V
b11110 U
b11110 /
0-
1'
#130
0'
#131
b11110 &
b11110 3
b11110 E
b11110 *
b11110 4
b11110 G
1-
1'
#132
0'
#133
b10011111 V
b11111 U
b11111 /
0-
1'
#134
0'
#135
b11111 &
b11111 3
b11111 E
b10011111 *
b10011111 4
b10011111 G
1-
1'
#136
0'
#137
b100000 /
0-
1'
#138
0'
#139
b10 >
1+
1'
#140
0'
#141
b10 C
b100 >
0+
1'
#142
0'
#143
b10000001 7
b10000001 F
b1 <
b1 D
b1000 >
b100 C
b1 @
1'
#144
0'
#145
1?
b0 7
b0 F
b0 <
b0 D
b10 >
b1000000100000000 N
b10000001 A
b10 @
b1000 C
1'
#146
0'
#147
b10 7
b10 F
b10 <
b10 D
0?
b100 >
b10 C
b10000001 B
b10000001 N
b0 A
1'
#148
0'
#149
b10000011 7
b10000011 F
b11 <
b11 D
b1000 >
b0 B
b1000000000 N
b10 A
b1 =
b1 L
b11 @
b100 C
1'
#150
0'
#151
1?
b0 7
b0 F
b0 <
b0 D
b10 >
b1000 C
b100 @
b10 B
b1000001100000010 N
b10000011 A
1'
#152
0'
#153
b100 7
b100 F
b100 <
b100 D
0?
b100 >
b10000011 B
b10000011 N
b0 A
b10 C
1'
#154
0'
#155
b10000101 7
b10000101 F
b101 <
b101 D
b1000 >
b100 C
b101 @
b10 =
b10 L
b0 B
b10000000000 N
b100 A
1'
#156
0'
#157
1?
b0 7
b0 F
b0 <
b0 D
b10 >
b100 B
b1000010100000100 N
b10000101 A
b110 @
b1000 C
1'
#158
0'
#159
b110 7
b110 F
b110 <
b110 D
0?
b100 >
b10 C
b10000101 B
b10000101 N
b0 A
1'
#160
0'
#161
b10000111 7
b10000111 F
b111 <
b111 D
b1000 >
b0 B
b11000000000 N
b110 A
b11 =
b11 L
b111 @
b100 C
1'
#162
0'
#163
1?
b0 7
b0 F
b0 <
b0 D
b10 >
b1000 C
b1000 @
b110 B
b1000011100000110 N
b10000111 A
1'
#164
0'
#165
b1000 7
b1000 F
b1000 <
b1000 D
0?
b100 >
b10000111 B
b10000111 N
b0 A
b10 C
1'
#166
0'
#167
b10001001 7
b10001001 F
b1001 <
b1001 D
b1000 >
b100 C
b1001 @
b100 =
b100 L
b0 B
b100000000000 N
b1000 A
1'
#168
0'
#169
1?
b0 7
b0 F
b0 <
b0 D
b10 >
b1000 B
b1000100100001000 N
b10001001 A
b1010 @
b1000 C
1'
#170
0'
#171
b1010 7
b1010 F
b1010 <
b1010 D
0?
b100 >
b10 C
b10001001 B
b10001001 N
b0 A
1'
#172
0'
#173
b10001011 7
b10001011 F
b1011 <
b1011 D
b1000 >
b0 B
b101000000000 N
b1010 A
b101 =
b101 L
b1011 @
b100 C
1'
#174
0'
#175
1?
b0 7
b0 F
b0 <
b0 D
b10 >
b1000 C
b1100 @
b1010 B
b1000101100001010 N
b10001011 A
1'
#176
0'
#177
b1100 7
b1100 F
b1100 <
b1100 D
0?
b100 >
b10001011 B
b10001011 N
b0 A
b10 C
1'
#178
0'
#179
b10001101 7
b10001101 F
b1101 <
b1101 D
b1000 >
b100 C
b1101 @
b110 =
b110 L
b0 B
b110000000000 N
b1100 A
1'
#180
0'
#181
1?
b0 7
b0 F
b0 <
b0 D
b10 >
b1100 B
b1000110100001100 N
b10001101 A
b1110 @
b1000 C
1'
#182
0'
#183
b1110 7
b1110 F
b1110 <
b1110 D
0?
b100 >
b10 C
b10001101 B
b10001101 N
b0 A
1'
#184
0'
#185
b10001111 7
b10001111 F
b1111 <
b1111 D
b1000 >
b0 B
b111000000000 N
b1110 A
b111 =
b111 L
b1111 @
b100 C
1'
#186
0'
#187
1?
b0 7
b0 F
b0 <
b0 D
b10 >
b1000 C
b10000 @
b1110 B
b1000111100001110 N
b10001111 A
1'
#188
0'
#189
b10000 7
b10000 F
b10000 <
b10000 D
0?
b100 >
b10001111 B
b10001111 N
b0 A
b10 C
1'
#190
0'
#191
b10010001 7
b10010001 F
b10001 <
b10001 D
b1000 >
b100 C
b10001 @
b1000 =
b1000 L
b0 B
b1000000000000 N
b10000 A
1'
#192
0'
#193
1?
b0 7
b0 F
b0 <
b0 D
b10 >
b10000 B
b1001000100010000 N
b10010001 A
b10010 @
b1000 C
1'
#194
0'
#195
b10010 7
b10010 F
b10010 <
b10010 D
0?
b100 >
b10 C
b10010001 B
b10010001 N
b0 A
1'
#196
0'
#197
b10010011 7
b10010011 F
b10011 <
b10011 D
b1000 >
b0 B
b1001000000000 N
b10010 A
b1001 =
b1001 L
b10011 @
b100 C
1'
#198
0'
#199
1?
b0 7
b0 F
b0 <
b0 D
b10 >
b1000 C
b10100 @
b10010 B
b1001001100010010 N
b10010011 A
1'
#200
0'
#201
b10100 7
b10100 F
b10100 <
b10100 D
0?
b100 >
b10010011 B
b10010011 N
b0 A
b10 C
1'
#202
0'
#203
b10010101 7
b10010101 F
b10101 <
b10101 D
b1000 >
b100 C
b10101 @
b1010 =
b1010 L
b0 B
b1010000000000 N
b10100 A
1'
#204
0'
#205
1?
b0 7
b0 F
b0 <
b0 D
b10 >
b10100 B
b1001010100010100 N
b10010101 A
b10110 @
b1000 C
1'
#206
0'
#207
b10110 7
b10110 F
b10110 <
b10110 D
0?
b100 >
b10 C
b10010101 B
b10010101 N
b0 A
1'
#208
0'
#209
b10010111 7
b10010111 F
b10111 <
b10111 D
b1000 >
b0 B
b1011000000000 N
b10110 A
b1011 =
b1011 L
b10111 @
b100 C
1'
#210
0'
#211
1?
b0 7
b0 F
b0 <
b0 D
b10 >
b1000 C
b11000 @
b10110 B
b1001011100010110 N
b10010111 A
1'
#212
0'
#213
b11000 7
b11000 F
b11000 <
b11000 D
0?
b100 >
b10010111 B
b10010111 N
b0 A
b10 C
1'
#214
0'
#215
b10011001 7
b10011001 F
b11001 <
b11001 D
b1000 >
b100 C
b11001 @
b1100 =
b1100 L
b0 B
b1100000000000 N
b11000 A
1'
#216
0'
#217
1?
b0 7
b0 F
b0 <
b0 D
b10 >
b11000 B
b1001100100011000 N
b10011001 A
b11010 @
b1000 C
1'
#218
0'
#219
b11010 7
b11010 F
b11010 <
b11010 D
0?
b100 >
b10 C
b10011001 B
b10011001 N
b0 A
1'
#220
0'
#221
b10011011 7
b10011011 F
b11011 <
b11011 D
b1000 >
b0 B
b1101000000000 N
b11010 A
b1101 =
b1101 L
b11011 @
b100 C
1'
#222
0'
#223
1?
b0 7
b0 F
b0 <
b0 D
b10 >
b1000 C
b11100 @
b11010 B
b1001101100011010 N
b10011011 A
1'
#224
0'
#225
b11100 7
b11100 F
b11100 <
b11100 D
0?
b100 >
b10011011 B
b10011011 N
b0 A
b10 C
1'
#226
0'
#227
b10011101 7
b10011101 F
b11101 <
b11101 D
b1000 >
b100 C
b11101 @
b1110 =
b1110 L
b0 B
b1110000000000 N
b11100 A
1'
#228
0'
#229
1?
b0 7
b0 F
b0 <
b0 D
b10 >
b11100 B
b1001110100011100 N
b10011101 A
b11110 @
b1000 C
1'
#230
0'
#231
b11110 7
b11110 F
b11110 <
b11110 D
0?
b100 >
b10 C
b10011101 B
b10011101 N
b0 A
1'
#232
0'
#233
b10011111 7
b10011111 F
b11111 <
b11111 D
b1000 >
b0 B
b1111000000000 N
b11110 A
b1111 =
b1111 L
b11111 @
b100 C
1'
#234
0'
#235
1?
b0 7
b0 F
b0 <
b0 D
b1 >
b0 T
b0 /
b1000 C
b0 @
1!
b11110 B
b1001111100011110 N
b10011111 A
1'
#236
0'
#237
0?
b10011111 B
b10011111 N
b0 A
b1 C
b1000000100000000 "
b1000000100000000 6
b1000000100000000 M
b0 %
b0 5
b0 K
1'
#238
b1 T
b10 /
b1 .
b1 2
b1000000100000000 S
b10000001 R
b10000001 (
b1000000100000000 )
0'
#239
b0 N
b0 B
b1000001100000010 "
b1000001100000010 6
b1000001100000010 M
b1 %
b1 5
b1 K
1'
#240
b10 T
b100 /
b10 .
b10 2
b1000001100000010 S
b1010000011 R
b1010000011 (
b1000001100000010 )
0'
#241
b1000010100000100 "
b1000010100000100 6
b1000010100000100 M
b10 %
b10 5
b10 K
1'
#242
b11 T
b110 /
b11 .
b11 2
b1000010100000100 S
b10010000101 R
b10010000101 (
b1000010100000100 )
0'
#243
b1000011100000110 "
b1000011100000110 6
b1000011100000110 M
b11 %
b11 5
b11 K
1'
#244
b100 T
b1000 /
b100 .
b100 2
b1000011100000110 S
b11010000111 R
b11010000111 (
b1000011100000110 )
0'
#245
b1000100100001000 "
b1000100100001000 6
b1000100100001000 M
b100 %
b100 5
b100 K
1'
#246
b101 T
b1010 /
b101 .
b101 2
b1000100100001000 S
b100010001001 R
b100010001001 (
b1000100100001000 )
0'
#247
b1000101100001010 "
b1000101100001010 6
b1000101100001010 M
b101 %
b101 5
b101 K
1'
#248
b110 T
b1100 /
b110 .
b110 2
b1000101100001010 S
b101010001011 R
b101010001011 (
b1000101100001010 )
0'
#249
b1000110100001100 "
b1000110100001100 6
b1000110100001100 M
b110 %
b110 5
b110 K
1'
#250
b111 T
b1110 /
b111 .
b111 2
b1000110100001100 S
b110010001101 R
b110010001101 (
b1000110100001100 )
0'
#251
b1000111100001110 "
b1000111100001110 6
b1000111100001110 M
b111 %
b111 5
b111 K
1'
#252
b1000 T
b10000 /
b1000 .
b1000 2
b1000111100001110 S
b111010001111 R
b111010001111 (
b1000111100001110 )
0'
#253
b1001000100010000 "
b1001000100010000 6
b1001000100010000 M
b1000 %
b1000 5
b1000 K
1'
#254
b1001 T
b10010 /
b1001 .
b1001 2
b1001000100010000 S
b1000010010001 R
b1000010010001 (
b1001000100010000 )
0'
#255
b1001001100010010 "
b1001001100010010 6
b1001001100010010 M
b1001 %
b1001 5
b1001 K
1'
#256
b1010 T
b10100 /
b1010 .
b1010 2
b1001001100010010 S
b1001010010011 R
b1001010010011 (
b1001001100010010 )
0'
#257
b1001010100010100 "
b1001010100010100 6
b1001010100010100 M
b1010 %
b1010 5
b1010 K
1'
#258
b1011 T
b10110 /
b1011 .
b1011 2
b1001010100010100 S
b1010010010101 R
b1010010010101 (
b1001010100010100 )
0'
#259
b1001011100010110 "
b1001011100010110 6
b1001011100010110 M
b1011 %
b1011 5
b1011 K
1'
#260
b1100 T
b11000 /
b1100 .
b1100 2
b1001011100010110 S
b1011010010111 R
b1011010010111 (
b1001011100010110 )
0'
#261
b1001100100011000 "
b1001100100011000 6
b1001100100011000 M
b1100 %
b1100 5
b1100 K
1'
#262
b1101 T
b11010 /
b1101 .
b1101 2
b1001100100011000 S
b1100010011001 R
b1100010011001 (
b1001100100011000 )
0'
#263
b1001101100011010 "
b1001101100011010 6
b1001101100011010 M
b1101 %
b1101 5
b1101 K
1'
#264
b1110 T
b11100 /
b1110 .
b1110 2
b1001101100011010 S
b1101010011011 R
b1101010011011 (
b1001101100011010 )
0'
#265
b1001110100011100 "
b1001110100011100 6
b1001110100011100 M
b1110 %
b1110 5
b1110 K
1'
#266
b1111 T
b11110 /
b1111 .
b1111 2
b1001110100011100 S
b1110010011101 R
b1110010011101 (
b1001110100011100 )
0'
#267
b1001111100011110 "
b1001111100011110 6
b1001111100011110 M
b1111 %
b1111 5
b1111 K
1'
#268
b1 V
b0 U
b1 0
b0 /
b10000 .
b10000 2
b1001111100011110 S
b1111010011111 R
b1111010011111 (
b1001111100011110 )
0'
#269
b1 7
b1 F
b0 &
b0 3
b0 E
b1 *
b1 4
b1 G
1-
1'
#270
0'
#271
b100000000 N
b1 A
b10000010 V
b1 U
b1 /
0-
1'
#272
0'
#273
b100000001 N
b1 B
b1 &
b1 3
b1 E
b10000010 *
b10000010 4
b10000010 G
1-
1'
#274
0'
#275
b11 V
b10 U
b10 /
0-
1'
#276
0'
#277
b10 &
b10 3
b10 E
b11 *
b11 4
b11 G
1-
1'
#278
0'
#279
b10000100 V
b11 U
b11 /
0-
1'
#280
0'
#281
b11 &
b11 3
b11 E
b10000100 *
b10000100 4
b10000100 G
1-
1'
#282
0'
#283
b101 V
b100 U
b100 /
0-
1'
#284
0'
#285
b100 &
b100 3
b100 E
b101 *
b101 4
b101 G
1-
1'
#286
0'
#287
b10000110 V
b101 U
b101 /
0-
1'
#288
0'
#289
b101 &
b101 3
b101 E
b10000110 *
b10000110 4
b10000110 G
1-
1'
#290
0'
#291
b111 V
b110 U
b110 /
0-
1'
#292
0'
#293
b110 &
b110 3
b110 E
b111 *
b111 4
b111 G
1-
1'
#294
0'
#295
b10001000 V
b111 U
b111 /
0-
1'
#296
0'
#297
b111 &
b111 3
b111 E
b10001000 *
b10001000 4
b10001000 G
1-
1'
#298
0'
#299
b1001 V
b1000 U
b1000 /
0-
1'
#300
0'
#301
b1000 &
b1000 3
b1000 E
b1001 *
b1001 4
b1001 G
1-
1'
#302
0'
#303
b10001010 V
b1001 U
b1001 /
0-
1'
#304
0'
#305
b1001 &
b1001 3
b1001 E
b10001010 *
b10001010 4
b10001010 G
1-
1'
#306
0'
#307
b1011 V
b1010 U
b1010 /
0-
1'
#308
0'
#309
b1010 &
b1010 3
b1010 E
b1011 *
b1011 4
b1011 G
1-
1'
#310
0'
#311
b10001100 V
b1011 U
b1011 /
0-
1'
#312
0'
#313
b1011 &
b1011 3
b1011 E
b10001100 *
b10001100 4
b10001100 G
1-
1'
#314
0'
#315
b1101 V
b1100 U
b1100 /
0-
1'
#316
0'
#317
b1100 &
b1100 3
b1100 E
b1101 *
b1101 4
b1101 G
1-
1'
#318
0'
#319
b10001110 V
b1101 U
b1101 /
0-
1'
#320
0'
#321
b1101 &
b1101 3
b1101 E
b10001110 *
b10001110 4
b10001110 G
1-
1'
#322
0'
#323
b1111 V
b1110 U
b1110 /
0-
1'
#324
0'
#325
b1110 &
b1110 3
b1110 E
b1111 *
b1111 4
b1111 G
1-
1'
#326
0'
#327
b10010000 V
b1111 U
b1111 /
0-
1'
#328
0'
#329
b1111 &
b1111 3
b1111 E
b10010000 *
b10010000 4
b10010000 G
1-
1'
#330
0'
#331
b10001 V
b10000 U
b10000 /
0-
1'
#332
0'
#333
b10000 &
b10000 3
b10000 E
b10001 *
b10001 4
b10001 G
1-
1'
#334
0'
#335
b10010010 V
b10001 U
b10001 /
0-
1'
#336
0'
#337
b10001 &
b10001 3
b10001 E
b10010010 *
b10010010 4
b10010010 G
1-
1'
#338
0'
#339
b10011 V
b10010 U
b10010 /
0-
1'
#340
0'
#341
b10010 &
b10010 3
b10010 E
b10011 *
b10011 4
b10011 G
1-
1'
#342
0'
#343
b10010100 V
b10011 U
b10011 /
0-
1'
#344
0'
#345
b10011 &
b10011 3
b10011 E
b10010100 *
b10010100 4
b10010100 G
1-
1'
#346
0'
#347
b10101 V
b10100 U
b10100 /
0-
1'
#348
0'
#349
b10100 &
b10100 3
b10100 E
b10101 *
b10101 4
b10101 G
1-
1'
#350
0'
#351
b10010110 V
b10101 U
b10101 /
0-
1'
#352
0'
#353
b10101 &
b10101 3
b10101 E
b10010110 *
b10010110 4
b10010110 G
1-
1'
#354
0'
#355
b10111 V
b10110 U
b10110 /
0-
1'
#356
0'
#357
b10110 &
b10110 3
b10110 E
b10111 *
b10111 4
b10111 G
1-
1'
#358
0'
